ichec_platform_core/__init__.py
ichec_platform_core/config_utils.py
ichec_platform_core/encryption.py
ichec_platform_core/logging_utils.py
ichec_platform_core/main_cli.py
ichec_platform_core/py.typed
ichec_platform_core/runtime.py
ichec_platform_core/test_utils.py
ichec_platform_core/url_utils.py
ichec_platform_core/filesystem/__init__.py
ichec_platform_core/filesystem/cli.py
ichec_platform_core/filesystem/filesystem.py
ichec_platform_core/network/__init__.py
ichec_platform_core/network/cli.py
ichec_platform_core/network/http_client.py
ichec_platform_core/network/utils.py
ichec_platform_core/project/__init__.py
ichec_platform_core/project/milestone.py
ichec_platform_core/project/person.py
ichec_platform_core/project/version.py
ichec_platform_core/serialization/__init__.py
ichec_platform_core/serialization/csv_utils.py
ichec_platform_core/serialization/json_utils.py
ichec_platform_core/serialization/key_value.py
ichec_platform_core/serialization/yaml_utils.py
ichec_platform_core/system/__init__.py
ichec_platform_core/system/cpu.py
ichec_platform_core/system/environment.py
ichec_platform_core/system/gpu.py
ichec_platform_core/system/process.py
ichec_platform_core/system/system_event.py
ichec_platform_core/system/cluster/__init__.py
ichec_platform_core/system/cluster/cluster_allocation.py
ichec_platform_core/system/cluster/node.py
ichec_platform_core/system/network/__init__.py
ichec_platform_core/system/network/host.py
ichec_platform_core/system/network/info.py
ichec_platform_core/version_control/__init__.py
ichec_platform_core/version_control/cli.py
ichec_platform_core/version_control/git.py
ichec_platform_core/version_control/gitlab.py
ichec_platform_core/version_control/gitlab_client.py
ichec_platform_core-0.0.3.dist-info/licenses/LICENSE.txt
ichec_platform_core-0.0.3.dist-info/METADATA
ichec_platform_core-0.0.3.dist-info/WHEEL
ichec_platform_core-0.0.3.dist-info/entry_points.txt
ichec_platform_core-0.0.3.dist-info/top_level.txt
ichec_platform_core-0.0.3.dist-info/RECORD
