Metadata-Version: 2.4
Name: ichec_platform_core
Version: 0.0.3
Summary: Utility library to support ICHEC Platform Engineering tools
Author: Irish Centre for High End Computing
Project-URL: Repository, https://git.ichec.ie/platform-engineering/ichec-platform-core
Project-URL: Homepage, https://git.ichec.ie/platform-engineering/ichec-platform-core
Keywords: HPC
Classifier: Development Status :: 3 - Alpha
Classifier: Programming Language :: Python :: 3
Classifier: License :: OSI Approved :: GNU General Public License v3 or later (GPLv3+)
Classifier: Operating System :: OS Independent
Classifier: Topic :: System :: Distributed Computing
Requires-Python: >=3.10
License-File: LICENSE.txt
Requires-Dist: PyYAML
Requires-Dist: pydantic
Requires-Dist: cryptography
Provides-Extra: test
Requires-Dist: pytest; extra == "test"
Requires-Dist: pytest-cov; extra == "test"
Requires-Dist: pytest-sugar; extra == "test"
Requires-Dist: pytest-mock; extra == "test"
Requires-Dist: black; extra == "test"
Requires-Dist: mypy; extra == "test"
Requires-Dist: flake8; extra == "test"
Requires-Dist: pylint; extra == "test"
Provides-Extra: types
Requires-Dist: types-PyYAML; extra == "types"
Dynamic: license-file
